<?xml version="1.0" encoding="UTF-8"?>
<!DOCTYPE mapper PUBLIC "-//mybatis.org//DTD Mapper 3.0//EN" "http://mybatis.org/dtd/mybatis-3-mapper.dtd">
<mapper namespace="top.warmheart.workerunion.server.dao.ProjectTeamMapper">
  <resultMap id="BaseResultMap" type="top.warmheart.workerunion.server.model.ProjectTeam">
    <!--
      WARNING - @mbg.generated
      This element is automatically generated by MyBatis Generator, do not modify.
    -->
    <id column="project_id" jdbcType="BIGINT" property="projectId" />
    <id column="staff_id" jdbcType="BIGINT" property="staffId" />
    <result column="team_role_id" jdbcType="BIGINT" property="teamRoleId" />
  </resultMap>
  <resultMap id="Staff3DtoMap" type="top.warmheart.workerunion.server.dto.Staff3Dto">
    <id column="id" jdbcType="BIGINT" property="id" />
    <result column="company_id" jdbcType="BIGINT" property="companyId" />
    <result column="name" jdbcType="VARCHAR" property="name" />
    <result column="sex" jdbcType="VARCHAR" property="sex" />
    <result column="job_no" jdbcType="VARCHAR" property="jobNo" />
    <result column="native_place" jdbcType="VARCHAR" property="nativePlace" />
    <result column="phone" jdbcType="VARCHAR" property="phone" />
    <result column="id_card_no" jdbcType="VARCHAR" property="idCardNo" />
    <result column="address" jdbcType="VARCHAR" property="address" />
    <result column="entry_date" jdbcType="DATE" property="entryDate" />
    <result column="career" jdbcType="VARCHAR" property="career" />
    <result column="birthday" jdbcType="DATE" property="birthday" />
    <result column="cst_create" jdbcType="TIMESTAMP" property="cstCreate" />
    <result column="cst_modified" jdbcType="TIMESTAMP" property="cstModified" />
    <result column="memo" jdbcType="VARCHAR" property="memo" />
    <result column="is_del" jdbcType="BIT" property="del" />
    <result column="type" jdbcType="VARCHAR" property="type" />
  </resultMap>
  <delete id="deleteByPrimaryKey" parameterType="map">
    <!--
      WARNING - @mbg.generated
      This element is automatically generated by MyBatis Generator, do not modify.
    -->
    delete from project_team
    where project_id = #{projectId,jdbcType=BIGINT}
      and staff_id = #{staffId,jdbcType=BIGINT}
  </delete>
  <insert id="insert" parameterType="top.warmheart.workerunion.server.model.ProjectTeam">
    <!--
      WARNING - @mbg.generated
      This element is automatically generated by MyBatis Generator, do not modify.
    -->
    insert into project_team (project_id, staff_id, team_role_id
      )
    values (#{projectId,jdbcType=BIGINT}, #{staffId,jdbcType=BIGINT}, #{teamRoleId,jdbcType=BIGINT}
      )
  </insert>
  <update id="updateByPrimaryKey" parameterType="top.warmheart.workerunion.server.model.ProjectTeam">
    <!--
      WARNING - @mbg.generated
      This element is automatically generated by MyBatis Generator, do not modify.
    -->
    update project_team
    set team_role_id = #{teamRoleId,jdbcType=BIGINT}
    where project_id = #{projectId,jdbcType=BIGINT}
      and staff_id = #{staffId,jdbcType=BIGINT}
  </update>
  <select id="selectByPrimaryKey" parameterType="map" resultMap="BaseResultMap">
    <!--
      WARNING - @mbg.generated
      This element is automatically generated by MyBatis Generator, do not modify.
    -->
    select project_id, staff_id, team_role_id
    from project_team
    where project_id = #{projectId,jdbcType=BIGINT}
      and staff_id = #{staffId,jdbcType=BIGINT}
  </select>
  <select id="selectAll" resultMap="BaseResultMap">
    <!--
      WARNING - @mbg.generated
      This element is automatically generated by MyBatis Generator, do not modify.
    -->
    select project_id, staff_id, team_role_id
    from project_team
  </select>
  <select id="selectByProjectRole" parameterType="map" resultMap="BaseResultMap">
    select project_id, staff_id, team_role_id
    from project_team
    where project_id = #{projectId,jdbcType=BIGINT}
      and team_role_id = #{teamRoleId,jdbcType=BIGINT}
  </select>
  <select id="selectListStaffByProjectId" resultMap="Staff3DtoMap">
    select s.id, s.company_id, s.name, s.sex, s.job_no, s.native_place, s.phone, s.id_card_no, s.address, 
    s.entry_date, s.career, s.birthday, s.cst_create, s.cst_modified, s.memo, s.is_del, tr.type as type
    from staff s join project_team pt on s.id=pt.staff_id left join team_role tr on tr.id=pt.team_role_id where project_id=#{projectId,jdbcType=BIGINT}
  </select>
  <select id="selectByProjectTeamType" resultMap="Staff3DtoMap">
    select s.id, s.company_id, s.name, s.sex, s.job_no, s.native_place, s.phone, s.id_card_no, s.address, 
    s.entry_date, s.career, s.birthday, s.cst_create, s.cst_modified, s.memo, s.is_del, tr.type as type
    from staff s join project_team pt on s.id=pt.staff_id and project_id=#{projectId,jdbcType=BIGINT} and s.is_del=false join team_role tr on tr.id=pt.team_role_id and tr.type=#{type,jdbcType=VARCHAR}
  </select>
  
</mapper>